meu_primeiro_pacote/__init__.py
meu_primeiro_pacote/apresentacao_app.py
meu_primeiro_pacote/boas_vindas.py
meu_primeiro_pacote-1.0.dist-info/METADATA
meu_primeiro_pacote-1.0.dist-info/WHEEL
meu_primeiro_pacote-1.0.dist-info/license.txt
meu_primeiro_pacote-1.0.dist-info/top_level.txt
meu_primeiro_pacote-1.0.dist-info/RECORD
